phisherman/__init__.py
phisherman/app.py
phisherman/exceptions.py
phisherman/py.typed
phisherman/route.py
phisherman.py-1.0.0.dist-info/WHEEL
phisherman.py-1.0.0.dist-info/METADATA
phisherman.py-1.0.0.dist-info/RECORD
