Metadata-Version: 2.1
Name: phisherman.py
Version: 1.0.0
Summary: Async API Wrapper for Phisherman.gg in Python
Home-page: https://github.com/QristaLabs/phisherman.py
License: MIT
Author: Vedrecide
Author-email: you@example.com
Requires-Python: >=3.8,<4.0
Classifier: License :: OSI Approved :: MIT License
Classifier: Operating System :: OS Independent
Classifier: Programming Language :: Python :: 3
Classifier: Programming Language :: Python :: 3.8
Classifier: Programming Language :: Python :: 3.9
Classifier: Programming Language :: Python :: Implementation :: CPython
Classifier: Typing :: Typed
Requires-Dist: aiohttp (>=3.8.1,<4.0.0)
Requires-Dist: taskipy (>=1.9.0,<2.0.0)
Project-URL: Repository, https://github.com/QristaLabs/phisherman.py
